epubcrush/__init__.py
epubcrush/__main__.py
epubcrush/epubcrush.py
epubcrush/filter.lua
epubcrush-4.0.1.dist-info/METADATA
epubcrush-4.0.1.dist-info/WHEEL
epubcrush-4.0.1.dist-info/entry_points.txt
epubcrush-4.0.1.dist-info/top_level.txt
epubcrush-4.0.1.dist-info/RECORD
