Metadata-Version: 2.1
Name: epubcrush
Version: 4.0.1
Summary: Compress EPUB files
Home-page: https://github.com/jncraton/epubcrush
Author: Jon Craton
Author-email: jon@joncraton.com
License: UNKNOWN
Platform: UNKNOWN
Classifier: Programming Language :: Python :: 3
Classifier: License :: OSI Approved :: MIT License
Classifier: Operating System :: OS Independent
Requires-Python: >=3.9
